fusionpy/__init__.py
fusionpy/main.py
fusionpy-0.0.1.dist-info/LICENSE
fusionpy-0.0.1.dist-info/METADATA
fusionpy-0.0.1.dist-info/WHEEL
fusionpy-0.0.1.dist-info/top_level.txt
fusionpy-0.0.1.dist-info/RECORD
