Metadata-Version: 2.1
Name: fusionpy
Version: 0.0.1
Summary: Python libralies for laser fusion development
Home-page: https://github.com/exfusion-dev
Author: astroysmr
Author-email: astro.yoshimura@gmail.com
License: MIT
Keywords: laser fusion
Classifier: License :: OSI Approved :: MIT License
Classifier: Programming Language :: Python :: 3.11
License-File: LICENSE
Requires-Dist: numpy
